jito_searcher_client/__init__.py
jito_searcher_client/async_searcher.py
jito_searcher_client/convert.py
jito_searcher_client/generated/__init__.py
jito_searcher_client/generated/auth_pb2.py
jito_searcher_client/generated/auth_pb2.pyi
jito_searcher_client/generated/auth_pb2_grpc.py
jito_searcher_client/generated/auth_pb2_grpc.pyi
jito_searcher_client/generated/block_engine_pb2.py
jito_searcher_client/generated/block_engine_pb2.pyi
jito_searcher_client/generated/block_engine_pb2_grpc.py
jito_searcher_client/generated/block_engine_pb2_grpc.pyi
jito_searcher_client/generated/block_pb2.py
jito_searcher_client/generated/block_pb2.pyi
jito_searcher_client/generated/block_pb2_grpc.py
jito_searcher_client/generated/block_pb2_grpc.pyi
jito_searcher_client/generated/bundle_pb2.py
jito_searcher_client/generated/bundle_pb2.pyi
jito_searcher_client/generated/bundle_pb2_grpc.py
jito_searcher_client/generated/bundle_pb2_grpc.pyi
jito_searcher_client/generated/packet_pb2.py
jito_searcher_client/generated/packet_pb2.pyi
jito_searcher_client/generated/packet_pb2_grpc.py
jito_searcher_client/generated/packet_pb2_grpc.pyi
jito_searcher_client/generated/relayer_pb2.py
jito_searcher_client/generated/relayer_pb2.pyi
jito_searcher_client/generated/relayer_pb2_grpc.py
jito_searcher_client/generated/relayer_pb2_grpc.pyi
jito_searcher_client/generated/searcher_pb2.py
jito_searcher_client/generated/searcher_pb2.pyi
jito_searcher_client/generated/searcher_pb2_grpc.py
jito_searcher_client/generated/searcher_pb2_grpc.pyi
jito_searcher_client/generated/shared_pb2.py
jito_searcher_client/generated/shared_pb2.pyi
jito_searcher_client/generated/shared_pb2_grpc.py
jito_searcher_client/generated/shared_pb2_grpc.pyi
jito_searcher_client/generated/shredstream_pb2.py
jito_searcher_client/generated/shredstream_pb2.pyi
jito_searcher_client/generated/shredstream_pb2_grpc.py
jito_searcher_client/generated/shredstream_pb2_grpc.pyi
jito_searcher_client/searcher.py
jito_searcher_client/token.py
jito_searcher_client_no_auth-0.1.9.dist-info/METADATA
jito_searcher_client_no_auth-0.1.9.dist-info/WHEEL
jito_searcher_client_no_auth-0.1.9.dist-info/RECORD
