Metadata-Version: 2.1
Name: jito_searcher_client_no_auth
Version: 0.1.9
Summary: Jito Labs Python Searcher Client
Author: Jito Labs
Author-email: support@jitolabs.com
Requires-Python: >=3.10,<4.0
Classifier: Programming Language :: Python :: 3
Classifier: Programming Language :: Python :: 3.10
Classifier: Programming Language :: Python :: 3.11
Classifier: Programming Language :: Python :: 3.12
Requires-Dist: black (>=24.8.0,<25.0.0)
Requires-Dist: click (>=8.1.3,<9.0.0)
Requires-Dist: grpcio (>=1.62.1,<2.0.0)
Requires-Dist: isort (>=5.13.2,<6.0.0)
Requires-Dist: protobuf (>=4.25.3,<5.0.0)
Requires-Dist: solana (==0.34.0)
